keyword_insights_mcp/__init__.py
keyword_insights_mcp/server.py
keyword_insights_mcp-0.1.0.dist-info/METADATA
keyword_insights_mcp-0.1.0.dist-info/WHEEL
keyword_insights_mcp-0.1.0.dist-info/entry_points.txt
keyword_insights_mcp-0.1.0.dist-info/RECORD
