Metadata-Version: 2.4
Name: keyword-insights-mcp
Version: 0.1.0
Summary: MCP server for Keyword Insights API
Requires-Python: >=3.10
Requires-Dist: httpx>=0.27.0
Requires-Dist: mcp>=1.0.0
